mlfns/__init__.py
mlfns/evaluate/__init__.py
mlfns/evaluate/inference.py
mlfns/evaluate/perf.py
mlfns/feature_eng/__init__.py
mlfns/plot/__init__.py
mlfns/plot/plot.py
mlfns/tests/__init__.py
mlfns/tests/test_simple.py
mlfns/train/__init__.py
mlfns/train/plot.py
mlfns-0.0.5.dist-info/LICENSE
mlfns-0.0.5.dist-info/METADATA
mlfns-0.0.5.dist-info/WHEEL
mlfns-0.0.5.dist-info/top_level.txt
mlfns-0.0.5.dist-info/RECORD
