Metadata-Version: 2.1
Name: mlfns
Version: 0.0.5
Summary: Machine Learning Python utility functions
Home-page: UNKNOWN
Author: Explore AI for Good
Author-email: gcloudex@gmail.com
License: UNKNOWN
Keywords: development artificial intelligent machine learning ai ml
Platform: UNKNOWN
Classifier: Development Status :: 3 - Alpha
Classifier: Intended Audience :: Developers
Classifier: Topic :: Software Development :: Libraries :: Python Modules
Classifier: Programming Language :: Python :: 3
Classifier: License :: OSI Approved :: MIT License
Classifier: Operating System :: OS Independent
